capm/__init__.py
capm/__main__.py
capm/config.py
capm/version.py
capm/commands/__init__.py
capm/commands/info.py
capm/entities/Config.py
capm/entities/PackageConfig.py
capm/entities/PackageDefinition.py
capm/entities/__init__.py
capm/package/__init__.py
capm/package/package.py
capm/package/definitions/ansible-lint.yml
capm/package/definitions/arm-ttk.yml
capm/package/definitions/asl-validator.yml
capm/package/definitions/cfn-lint.yml
capm/package/definitions/checkov.yml
capm/package/definitions/clang-format.yml
capm/package/definitions/codelimit.yml
capm/package/definitions/cpplint.yml
capm/package/definitions/jscpd.yml
capm/package/definitions/mypy.yml
capm/package/definitions/radon.yml
capm/package/definitions/ruff.yml
capm/package/definitions/tokei.yml
capm/package/definitions/trivy.yml
capm/package/definitions/ubuntu.yml
capm/package/definitions/xenon.yml
capm/utils/Spinner.py
capm/utils/__init__.py
capm/utils/cli_utils.py
capm/utils/utils.py
capm-0.9.2.dist-info/METADATA
capm-0.9.2.dist-info/WHEEL
capm-0.9.2.dist-info/entry_points.txt
capm-0.9.2.dist-info/licenses/LICENSE
capm-0.9.2.dist-info/RECORD
