Metadata-Version: 2.4
Name: capm
Version: 0.9.2
Summary: Code Analysis Package Manager
Project-URL: Changelog, https://github.com/getcapm/capm/blob/master/CHANGELOG.md
Project-URL: Documentation, https://getcapm.github.io
Project-URL: Source, https://github.com/getcapm/capm
Author-email: Rob van der Leek <robvanderleek@gmail.com>
License-Expression: GPL-3.0-or-later
License-File: LICENSE
Requires-Python: <3.15,>=3.10
Requires-Dist: click>=8.3.1
Requires-Dist: docker>=7.1.0
Requires-Dist: halo>=0.0.31
Requires-Dist: inquirer>=3.4.1
Requires-Dist: pyyaml>=6.0.3
Requires-Dist: typer>=0.21.0
